ape_etherscan/__init__.py
ape_etherscan/client.py
ape_etherscan/config.py
ape_etherscan/dependency.py
ape_etherscan/exceptions.py
ape_etherscan/explorer.py
ape_etherscan/py.typed
ape_etherscan/query.py
ape_etherscan/types.py
ape_etherscan/utils.py
ape_etherscan/verify.py
ape_etherscan/version.py
ape_etherscan-0.8.5.dist-info/licenses/LICENSE
ape_etherscan-0.8.5.dist-info/METADATA
ape_etherscan-0.8.5.dist-info/WHEEL
ape_etherscan-0.8.5.dist-info/top_level.txt
ape_etherscan-0.8.5.dist-info/RECORD
