Metadata-Version: 2.4
Name: ape-etherscan
Version: 0.8.5
Summary: ape-etherscan: Etherscan Explorer Plugin for Ethereum-based networks
Home-page: https://github.com/ApeWorX/ape-etherscan
Author: ApeWorX Ltd.
Author-email: admin@apeworx.io
License: Apache-2.0
Keywords: ethereum
Classifier: Development Status :: 5 - Production/Stable
Classifier: Intended Audience :: Developers
Classifier: License :: OSI Approved :: MIT License
Classifier: Natural Language :: English
Classifier: Operating System :: MacOS
Classifier: Operating System :: POSIX
Classifier: Programming Language :: Python :: 3
Classifier: Programming Language :: Python :: 3.9
Classifier: Programming Language :: Python :: 3.10
Classifier: Programming Language :: Python :: 3.11
Classifier: Programming Language :: Python :: 3.12
Classifier: Programming Language :: Python :: 3.13
Requires-Python: >=3.9,<4
License-File: LICENSE
Requires-Dist: eth-ape<0.9,>=0.8.21
Requires-Dist: ethpm_types
Requires-Dist: requests
Requires-Dist: yarl
Provides-Extra: test
Requires-Dist: ape-arbitrum; extra == "test"
Requires-Dist: ape-base; extra == "test"
Requires-Dist: ape-blast; extra == "test"
Requires-Dist: ape-bsc; extra == "test"
Requires-Dist: ape-fantom; extra == "test"
Requires-Dist: ape-optimism; extra == "test"
Requires-Dist: ape-polygon; extra == "test"
Requires-Dist: ape-polygon-zkevm; extra == "test"
Requires-Dist: ape-scroll; extra == "test"
Requires-Dist: ape-infura; extra == "test"
Requires-Dist: ape-solidity; extra == "test"
Requires-Dist: pytest>=6.0; extra == "test"
Requires-Dist: pytest-xdist; extra == "test"
Requires-Dist: pytest-cov; extra == "test"
Requires-Dist: hypothesis<7,>=6.2.0; extra == "test"
Requires-Dist: pytest-mock; extra == "test"
Provides-Extra: lint
Requires-Dist: black<25,>=24.10.0; extra == "lint"
Requires-Dist: mypy<2,>=1.13.0; extra == "lint"
Requires-Dist: types-requests>=2.28.7; extra == "lint"
Requires-Dist: types-setuptools; extra == "lint"
Requires-Dist: types-PyYAML; extra == "lint"
Requires-Dist: flake8<8,>=7.1.1; extra == "lint"
Requires-Dist: flake8-breakpoint<2,>=1.1.0; extra == "lint"
Requires-Dist: flake8-print<6,>=5.0.0; extra == "lint"
Requires-Dist: flake8-pydantic; extra == "lint"
Requires-Dist: flake8-type-checking; extra == "lint"
Requires-Dist: isort<6,>=5.13.2; extra == "lint"
Requires-Dist: mdformat>=0.7.19; extra == "lint"
Requires-Dist: mdformat-gfm>=0.3.5; extra == "lint"
Requires-Dist: mdformat-frontmatter>=0.4.1; extra == "lint"
Requires-Dist: mdformat-pyproject>=0.0.2; extra == "lint"
Provides-Extra: doc
Requires-Dist: sphinx-ape; extra == "doc"
Provides-Extra: release
Requires-Dist: setuptools>=75.6.0; extra == "release"
Requires-Dist: setuptools-scm; extra == "release"
Requires-Dist: wheel; extra == "release"
Requires-Dist: twine; extra == "release"
Provides-Extra: dev
Requires-Dist: ape-arbitrum; extra == "dev"
Requires-Dist: ape-base; extra == "dev"
Requires-Dist: ape-blast; extra == "dev"
Requires-Dist: ape-bsc; extra == "dev"
Requires-Dist: ape-fantom; extra == "dev"
Requires-Dist: ape-optimism; extra == "dev"
Requires-Dist: ape-polygon; extra == "dev"
Requires-Dist: ape-polygon-zkevm; extra == "dev"
Requires-Dist: ape-scroll; extra == "dev"
Requires-Dist: ape-infura; extra == "dev"
Requires-Dist: ape-solidity; extra == "dev"
Requires-Dist: pytest>=6.0; extra == "dev"
Requires-Dist: pytest-xdist; extra == "dev"
Requires-Dist: pytest-cov; extra == "dev"
Requires-Dist: hypothesis<7,>=6.2.0; extra == "dev"
Requires-Dist: pytest-mock; extra == "dev"
Requires-Dist: black<25,>=24.10.0; extra == "dev"
Requires-Dist: mypy<2,>=1.13.0; extra == "dev"
Requires-Dist: types-requests>=2.28.7; extra == "dev"
Requires-Dist: types-setuptools; extra == "dev"
Requires-Dist: types-PyYAML; extra == "dev"
Requires-Dist: flake8<8,>=7.1.1; extra == "dev"
Requires-Dist: flake8-breakpoint<2,>=1.1.0; extra == "dev"
Requires-Dist: flake8-print<6,>=5.0.0; extra == "dev"
Requires-Dist: flake8-pydantic; extra == "dev"
Requires-Dist: flake8-type-checking; extra == "dev"
Requires-Dist: isort<6,>=5.13.2; extra == "dev"
Requires-Dist: mdformat>=0.7.19; extra == "dev"
Requires-Dist: mdformat-gfm>=0.3.5; extra == "dev"
Requires-Dist: mdformat-frontmatter>=0.4.1; extra == "dev"
Requires-Dist: mdformat-pyproject>=0.0.2; extra == "dev"
Requires-Dist: sphinx-ape; extra == "dev"
Requires-Dist: setuptools>=75.6.0; extra == "dev"
Requires-Dist: setuptools-scm; extra == "dev"
Requires-Dist: wheel; extra == "dev"
Requires-Dist: twine; extra == "dev"
Requires-Dist: commitizen; extra == "dev"
Requires-Dist: pre-commit; extra == "dev"
Requires-Dist: pytest-watch; extra == "dev"
Requires-Dist: IPython; extra == "dev"
Requires-Dist: ipdb; extra == "dev"
Dynamic: author
Dynamic: author-email
Dynamic: classifier
Dynamic: description
Dynamic: description-content-type
Dynamic: home-page
Dynamic: keywords
Dynamic: license
Dynamic: license-file
Dynamic: provides-extra
Dynamic: requires-dist
Dynamic: requires-python
Dynamic: summary
